{
  "plugins": {
    "blink.cmp": {
      "rev": "4e9edba1b1cef1585cc65e54287229e5d34e4df8",
      "src": "https://github.com/Saghen/blink.cmp",
      "version": "1.0.0 - 2.0.0"
    },
    "blink.nvim": {
      "rev": "16a597e89cf2ee6215a392c5bc5a945477015534",
      "src": "https://github.com/Saghen/blink.nvim"
    },
    "conform.nvim": {
      "rev": "973f3cb73887d510321653044791d7937c7ec0fa",
      "src": "https://github.com/stevearc/conform.nvim"
    },
    "fzf-lua": {
      "rev": "c9a2deb7bf2d8deaf56a229ff9c7bfeffa8d7d53",
      "src": "https://github.com/ibhagwan/fzf-lua"
    },
    "gitsigns.nvim": {
      "rev": "b01433169be710d6c69f7b4ee264d9670698b831",
      "src": "https://github.com/lewis6991/gitsigns.nvim"
    },
    "lazydev.nvim": {
      "rev": "2367a6c0a01eb9edb0464731cc0fb61ed9ab9d2c",
      "src": "https://github.com/folke/lazydev.nvim"
    },
    "mason.nvim": {
      "rev": "3671ab0d40aa5bd24b1686562bd0a23391ecf76a",
      "src": "https://github.com/mason-org/mason.nvim"
    },
    "mini.ai": {
      "rev": "1cd4f021a05c29acd4ab511c0981da14217daf38",
      "src": "https://github.com/echasnovski/mini.ai"
    },
    "mini.pairs": {
      "rev": "1e1ca3f60f58d4050bf814902b472eec9963a5dd",
      "src": "https://github.com/echasnovski/mini.pairs"
    },
    "miniharp.nvim": {
      "rev": "29c50dd622e98e2fc5e12f71fba29e3fc34f1425",
      "src": "https://github.com/vieitesss/miniharp.nvim"
    },
    "neovim": {
      "rev": "72befaffeac38db7bdd49e0549eaa2c4806dd878",
      "src": "https://github.com/rose-pine/neovim"
    },
    "nui.nvim": {
      "rev": "de740991c12411b663994b2860f1a4fd0937c130",
      "src": "https://github.com/MunifTanjim/nui.nvim"
    },
    "nvim-lspconfig": {
      "rev": "4d3b3bb8815fbe37bcaf3dbdb12a22382bc11ebe",
      "src": "https://github.com/neovim/nvim-lspconfig"
    },
    "nvim-tree.lua": {
      "rev": "2f1010ca7764ba2dc2ebe42b34c118631a453076",
      "src": "https://github.com/nvim-tree/nvim-tree.lua"
    },
    "nvim-treesitter": {
      "rev": "42fc28ba918343ebfd5565147a42a26580579482",
      "src": "https://github.com/nvim-treesitter/nvim-treesitter"
    },
    "nvim-web-devicons": {
      "rev": "4a8369f4c78ef6f6f895f0cec349e48f74330574",
      "src": "https://github.com/nvim-tree/nvim-web-devicons"
    },
    "nvim-window-picker": {
      "rev": "6382540b2ae5de6c793d4aa2e3fe6dbb518505ec",
      "src": "https://github.com/s1n7ax/nvim-window-picker"
    },
    "plenary.nvim": {
      "rev": "b9fd5226c2f76c951fc8ed5923d85e4de065e509",
      "src": "https://github.com/nvim-lua/plenary.nvim"
    },
    "vague.nvim": {
      "rev": "c1ab4d4891ff3a27deba6a80222d895ac8ffb2e5",
      "src": "https://github.com/vague-theme/vague.nvim"
    },
    "vim-fugitive": {
      "rev": "61b51c09b7c9ce04e821f6cf76ea4f6f903e3cf4",
      "src": "https://github.com/tpope/vim-fugitive"
    }
  }
}